sc_common_interface/CommonOa.py
sc_common_interface/LiveCommonInterface.py
sc_common_interface/McCommonInterface.py
sc_common_interface/OperaMysql.py
sc_common_interface/OperaRedis.py
sc_common_interface/Platform.py
sc_common_interface/PostCommonInterface.py
sc_common_interface/ScPulsar.py
sc_common_interface/ScWebsocket.py
sc_common_interface/__init__.py
sc_common_interface-3.1.4.dist-info/METADATA
sc_common_interface-3.1.4.dist-info/WHEEL
sc_common_interface-3.1.4.dist-info/top_level.txt
sc_common_interface-3.1.4.dist-info/RECORD
