Metadata-Version: 2.1
Name: sc-common-interface
Version: 3.1.4
Summary: SC贴文销售公用的接口
Home-page: UNKNOWN
Author: river
License: UNKNOWN
Platform: UNKNOWN
Requires-Dist: requests (>=2.0.0)
Requires-Dist: jsonpath (>=0.82)
Requires-Dist: websocket-client (>=1.6.1)
Requires-Dist: websockets (>=15.0.1)
